<?xml version="1.0" encoding="utf-8"?>
<state><branchmode>0000001111</branchmode><vparam><tau>0.29999999999999999</tau><taueff>0.25495382696655799</taueff><etrial>-2.2533824757550369</etrial><eref>-2.2524063897819819</eref><branchmax>-2.2519221075031566</branchmax><branchcutoff>12.5</branchcutoff><branchfilter>8.3333333333333339</branchfilter><sigma>0.24000000000000005</sigma><acc_energy>0.042606128526959143</acc_energy><acc_samples>-430.2091361660797</acc_samples></vparam><iparam><warmupsteps>0</warmupsteps><energyupdateinterval>1</energyupdateinterval><counter>1</counter><targetwalkers>2048</targetwalkers><maxwalkers>2049</maxwalkers><minwalkers>205</minwalkers><brnachinterval>1</brnachinterval></iparam><energy><value>-430.2091361660797</value><value_squared>969.01632448143619</value_squared><weight>191</weight></energy><variance><value>11.309143406723397</value><value_squared>1.0508305512492424</value_squared><weight>201</weight></variance><r2accepted><value>1252248.0322095877</value><value_squared>7841679846.8483744</value_squared><weight>201</weight></r2accepted><r2proposed><value>1473499.7867364944</value><value_squared>10857337051.330317</value_squared><weight>201</weight></r2proposed></state>