<?xml version="1.0" encoding="utf-8"?>
<state><branchmode>0000001111</branchmode><vparam><tau>0.02</tau><taueff>0.019909795858858773</taueff><etrial>-2.2447892264630731</etrial><eref>-2.2462551441455698</eref><branchmax>-2.2444770393251141</branchmax><branchcutoff>15</branchcutoff><branchfilter>10</branchfilter><sigma>0.20000000000000001</sigma><acc_energy>0.060110441587160168</acc_energy><acc_samples>-2136.1868639776162</acc_samples></vparam><iparam><warmupsteps>0</warmupsteps><energyupdateinterval>1</energyupdateinterval><counter>1</counter><targetwalkers>4096</targetwalkers><maxwalkers>2049</maxwalkers><minwalkers>205</minwalkers><brnachinterval>1</brnachinterval></iparam><energy><value>-2136.1868639776162</value><value_squared>4798.4299215608989</value_squared><weight>951</weight></energy><variance><value>51.65885619491381</value><value_squared>3.3498990507684425</value_squared><weight>1001</weight></variance><r2accepted><value>977218.70805936411</value><value_squared>955000052.05270898</value_squared><weight>1001</weight></r2accepted><r2proposed><value>981646.1353867224</value><value_squared>963673538.46160233</value_squared><weight>1001</weight></r2proposed></state>